README.rst
setup.py
input_algorithms/__init__.py
input_algorithms/dictobj.py
input_algorithms/errors.py
input_algorithms/field_spec.py
input_algorithms/many_item_spec.py
input_algorithms/meta.py
input_algorithms/spec_base.py
input_algorithms/validators.py
input_algorithms.egg-info/PKG-INFO
input_algorithms.egg-info/SOURCES.txt
input_algorithms.egg-info/dependency_links.txt
input_algorithms.egg-info/requires.txt
input_algorithms.egg-info/top_level.txt