Metadata-Version: 1.0
Name: input-algorithms
Version: 0.5.9
Summary: Thin DSL for creating input_algorithms
Home-page: http://input_algorithms.readthedocs.org
Author: Stephen Moore
Author-email: stephen@delfick.com
License: MIT
Keywords: yaml specification
Platform: UNKNOWN
